data_scout/__init__.py
data_scout/exceptions.py
data_scout/executor.py
data_scout/scout.py
data_scout/connectors/__init__.py
data_scout/connectors/big_query.py
data_scout/connectors/connector.py
data_scout/connectors/csv.py
data_scout/connectors/data_source_type.py
data_scout/connectors/excel.py
data_scout/connectors/join.py
data_scout/connectors/sql.py
data_scout/transformations/__init__.py
data_scout/transformations/_utils.py
data_scout/transformations/array.py
data_scout/transformations/comparison.py
data_scout/transformations/count.py
data_scout/transformations/data.py
data_scout/transformations/datetime.py
data_scout/transformations/dictionary.py
data_scout/transformations/extract.py
data_scout/transformations/filter.py
data_scout/transformations/format.py
data_scout/transformations/groupby.py
data_scout/transformations/literal.py
data_scout/transformations/math.py
data_scout/transformations/math_custom.py
data_scout/transformations/pivot.py
data_scout/transformations/preprocessing.py
data_scout/transformations/replace.py
data_scout/transformations/sort.py
data_scout/transformations/statistics.py
data_scout/transformations/string.py
data_scout/transformations/transformation.py
data_scout/transformations/window.py
data_scout-0.1.1.dist-info/LICENSE
data_scout-0.1.1.dist-info/METADATA
data_scout-0.1.1.dist-info/WHEEL
data_scout-0.1.1.dist-info/top_level.txt
data_scout-0.1.1.dist-info/RECORD
