Metadata-Version: 2.1
Name: data-scout
Version: 0.1.1
Summary: This package provides the tools to quickly setup a scalable and readable data pipeline that can be run on different platforms.
Home-page: https://github.com/janthiemen/data_scout/
Author: Jan Thiemen Postema
Author-email: info@scoutline.org
License: UNKNOWN
Project-URL: Bug Tracker, https://github.com/janthiemen/data_scout/issues
Project-URL: Documentation, https://janthiemen.github.io/data_scout/
Project-URL: Source Code, https://github.com/janthiemen/data_scout/
Keywords: data,data preperation
Platform: UNKNOWN
Classifier: Programming Language :: Python :: 3
Classifier: License :: OSI Approved :: MIT License
Classifier: Operating System :: OS Independent
Requires-Python: >=3.6
License-File: LICENSE
Requires-Dist: pandas
Requires-Dist: xlrd
Requires-Dist: openpyxl
Requires-Dist: sqlalchemy
Requires-Dist: pyparsing
Requires-Dist: text-unidecode
Requires-Dist: scikit-learn
Provides-Extra: dev
Requires-Dist: nose2 ; extra == 'dev'
